{
    "$schema": "https://schema.management.azure.com/schemas/2015-01-01/deploymentTemplate.json#",
    "contentVersion": "1.0.0.0",
    "parameters": {
        "applicationGatewayName": {
            "type": "string"
        },
        "aseInboundIpAddress": {
            "type": "string",
            "metadata": {
                "description": "The inbound IP address of your ILB ASE"
            }
        },

        "virtualNetworkName": {
            "type": "string",
            "defaultValue": "ilb-ase-vnet"
        },
        "subnetName": {
            "type": "string",
            "defaultValue": "gateway-subnet"
        },
        "location": {
            "type": "string",
            "defaultValue": "eastus"
        },
        "tier": {
            "type": "string",
            "defaultValue": "Standard_v2"
        },
        "skuSize": {
            "type": "string",
            "defaultValue": "Standard_v2"
        },
        "capacity": {
            "type": "int",
            "defaultValue": 2
        },
        "zones": {
            "type": "array",
            "defaultValue": []
        },
        "publicIpAddressName": {
            "type": "string",
            "defaultValue": "public-ip-address"
        },
        "sku": {
            "type": "string",
            "defaultValue": "Standard"
        },
        "allocationMethod": {
            "type": "string",
            "defaultValue": "Static"
        },
        "publicIpZones": {
            "type": "array",
            "defaultValue": []
        }
    },
    "variables": {
        "vnetId": "[resourceId(subscription().subscriptionId, resourceGroup().name, 'Microsoft.Networks/virtualNetworks', parameters('virtualNetworkName'))]",
        "publicIPRef": "[resourceId('Microsoft.Network/publicIPAddresses/', parameters('publicIpAddressName'))]",
        "subnetRef": "[concat(variables('vnetId'), '/subnets/', parameters('subnetName'))]",
        "applicationGatewayId": "[resourceId('Microsoft.Network/applicationGateways', parameters('applicationGatewayName'))]"
    },
    "resources": [
        {
            "name": "[parameters('applicationGatewayName')]",
            "type": "Microsoft.Network/applicationGateways",
            "apiVersion": "2019-09-01",
            "location": "[parameters('location')]",
            "zones": "[parameters('zones')]",
            "dependsOn": [
                "[concat('Microsoft.Network/publicIPAddresses/', parameters('publicIpAddressName'))]"
            ],
            "tags": {},
            "properties": {
                "sku": {
                    "name": "[parameters('skuSize')]",
                    "tier": "[parameters('tier')]",
                    "capacity": "[parameters('capacity')]"
                },
                "gatewayIPConfigurations": [
                    {
                        "name": "appGatewayIpConfig",
                        "properties": {
                            "subnet": {
                                "id": "[variables('subnetRef')]"
                            }
                        }
                    }
                ],
                "frontendIPConfigurations": [
                    {
                        "name": "appGwPublicFrontendIp",
                        "properties": {
                            "PublicIPAddress": {
                                "id": "[variables('publicIPRef')]"
                            }
                        }
                    }
                ],
                "frontendPorts": [
                    {
                        "name": "port_80",
                        "properties": {
                            "Port": 80
                        }
                    }
                ],
                "backendAddressPools": [
                    {
                        "name": "backend-pool-for-ase",
                        "properties": {
                            "backendAddresses": [
                                {
                                    "ipAddress": "[parameters('aseInboundIpAddress')]",
                                    "fqdn": null
                                }
                            ]
                        }
                    }
                ],
                "backendHttpSettingsCollection": [
                    {
                        "name": "basic-http-setting",
                        "properties": {
                            "Port": 80,
                            "Protocol": "Http",
                            "cookieBasedAffinity": "Disabled",
                            "requestTimeout": 20,
                            "hostName": "ilb-ase-domain.test",
                            "probe": {
                                "id": "[concat(variables('applicationGatewayId'), '/probes/probe-for-basic-http-setting')]"
                            }
                        }
                    }
                ],
                "httpListeners": [
                    {
                        "name": "listener-name",
                        "properties": {
                            "frontendIPConfiguration": {
                                "id": "[concat(variables('applicationGatewayId'), '/frontendIPConfigurations/appGwPublicFrontendIp')]"
                            },
                            "frontendPort": {
                                "id": "[concat(variables('applicationGatewayId'), '/frontendPorts/port_80')]"
                            },
                            "protocol": "Http",
                            "sslCertificate": null
                        }
                    }
                ],
                "requestRoutingRules": [
                    {
                        "Name": "routing-rule-for-ase-name",
                        "properties": {
                            "RuleType": "Basic",
                            "httpListener": {
                                "id": "[concat(variables('applicationGatewayId'), '/httpListeners/listener-name')]"
                            },
                            "priority": null,
                            "backendAddressPool": {
                                "id": "[concat(variables('applicationGatewayId'), '/backendAddressPools/backend-pool-for-ase')]"
                            },
                            "backendHttpSettings": {
                                "id": "[concat(variables('applicationGatewayId'), '/backendHttpSettingsCollection/basic-http-setting')]"
                            }
                        }
                    }
                ],
                "enableHttp2": false,
                "sslCertificates": [],
                "probes": [
                    {
                        "name": "probe-for-basic-http-setting",
                        "properties": {
                            "backendHttpSettings": [
                                {
                                    "id": "[concat(variables('applicationGatewayId'), '/backendHttpSettingsCollection/basic-http-setting')]"
                                }
                            ],
                            "interval": 30,
                            "minServers": 0,
                            "path": "/",
                            "protocol": "Http",
                            "timeout": 30,
                            "unhealthyThreshold": 3,
                            "pickHostNameFromBackendHttpSettings": false,
                            "host": "ilb-ase-domain.test"
                        }
                    }
                ]
            }
        },
        {
            "apiVersion": "2020-08-01",
            "type": "Microsoft.Network/publicIPAddresses",
            "name": "[parameters('publicIpAddressName')]",
            "location": "[parameters('location')]",
            "sku": {
                "name": "[parameters('sku')]"
            },
            "zones": "[parameters('publicIpZones')]",
            "properties": {
                "publicIPAllocationMethod": "[parameters('allocationMethod')]"
            }
        }
    ]
}